{
  "collectionName": "components_page_related_articles",
  "info": {
    "displayName": "RelatedArticle",
    "icon": "attachment",
    "description": ""
  },
  "options": {},
  "attributes": {
    "categories": {
      "type": "relation",
      "relation": "oneToMany",
      "target": "api::category.category"
    },
    "IconImage": {
      "allowedTypes": [
        "images",
        "files",
        "videos",
        "audios"
      ],
      "type": "media",
      "multiple": true
    }
  }
}
